es_pii_tool/__init__.py
es_pii_tool/base.py
es_pii_tool/cli.py
es_pii_tool/defaults.py
es_pii_tool/exceptions.py
es_pii_tool/job.py
es_pii_tool/py.typed
es_pii_tool/trackables.py
es_pii_tool/commands/__init__.py
es_pii_tool/commands/from_yaml.py
es_pii_tool/helpers/__init__.py
es_pii_tool/helpers/elastic_api.py
es_pii_tool/helpers/steps.py
es_pii_tool/helpers/utils.py
es_pii_tool/redacters/__init__.py
es_pii_tool/redacters/index.py
es_pii_tool/redacters/snapshot.py
es_pii_tool/redacters/steps.py
es_pii_tool-0.11.0.dist-info/METADATA
es_pii_tool-0.11.0.dist-info/WHEEL
es_pii_tool-0.11.0.dist-info/entry_points.txt
es_pii_tool-0.11.0.dist-info/licenses/LICENSE
es_pii_tool-0.11.0.dist-info/RECORD
