Metadata-Version: 2.3
Name: es-pii-tool
Version: 0.11.0
Summary: Redacting field data from your Elasticsearch indices and Searchable Snapshots
Project-URL: Homepage, https://github.com/elastic/es-pii-tool
Project-URL: Bug Tracker, https://github.com/elastic/es-pii-tool/issues
Author-email: Elastic <info@elastic.co>
License: Apache-2.0
License-File: LICENSE
Keywords: elasticsearch,index,pii,redact
Classifier: Intended Audience :: Developers
Classifier: Intended Audience :: System Administrators
Classifier: License :: OSI Approved :: Apache Software License
Classifier: Operating System :: OS Independent
Classifier: Programming Language :: Python
Classifier: Programming Language :: Python :: 3.8
Classifier: Programming Language :: Python :: 3.9
Classifier: Programming Language :: Python :: 3.10
Classifier: Programming Language :: Python :: 3.11
Classifier: Programming Language :: Python :: 3.12
Requires-Python: >=3.8
Requires-Dist: es-client>=8.17.4
Requires-Dist: es-wait>=0.11.0
Provides-Extra: doc
Requires-Dist: sphinx; extra == 'doc'
Requires-Dist: sphinx-rtd-theme; extra == 'doc'
Provides-Extra: test
Requires-Dist: es-testbed==0.9.0; extra == 'test'
Requires-Dist: pytest-cov; extra == 'test'
Requires-Dist: pytest>=7.2.1; extra == 'test'
Requires-Dist: python-dotenv==1.0.1; extra == 'test'
Requires-Dist: requests; extra == 'test'
